Metadata-Version: 2.4
Name: zk-rag
Version: 2.6.1
Summary: zk-rag is a command-line chat tool for your zettelkasten
Author-email: Stacey Vetzal <stacey@vetzal.com>
Project-URL: Homepage, https://github.com/svetzal/zk-rag
Project-URL: Issues, https://github.com/svetzal/zk-rag/issues
Classifier: Programming Language :: Python :: 3
Classifier: License :: OSI Approved :: MIT License
Classifier: Operating System :: OS Independent
Requires-Python: >=3.11
Requires-Dist: chromadb==0.6.3
Requires-Dist: chroma-hnswlib==0.7.6
Requires-Dist: pyyaml
Requires-Dist: mojentic>=0.5.2
Requires-Dist: PySide6>=6.6.0
Requires-Dist: rich
